rtl/data_mem.v
module data_mem(
    input  wire 		clk,       // System clock
    input  wire 		memRead,   // Control signal to read
    input  wire 		memWrite,  // Control signal to write
    input  wire [31:0] 	addr,      // Address from ALU calculation
    input  wire [31:0] 	writeData, // Data from register rs2 to write into memory
    output wire [31:0] 	readData   // Data read from memory sent back to register file
);

    // Create a data memory array of 64 words 
    reg [31:0] ram [0:63];
    
    integer i;
    initial begin
        for (i = 0; i < 64; i = i + 1)
            ram[i] = 32'h00000000;
    end

    // Asynchronous continuous read when memRead is enabled
    // 7:2 -> 6 bits for 64 entries
    assign readData = (memRead) ? ram[addr[7:2]] : 32'h00000000;  

    // Synchronous write on falling edge to protect single-cycle timing paths
    always @(negedge clk) begin
        if (memWrite) begin
            ram[addr[7:2]] <= writeData;
        end
    end

    //Simulation-only alignment check
    always @(posedge clk) begin
        if ((memRead || memWrite) && (addr[1:0] != 2'b00)) begin
            $display("WARNING: Unaligned memory access at addr=%h", addr);
        end
    end

endmodule

rtl/alu32.v
module alu32(
	input  wire [31:0]	a,          // Operand A (from rs1)
	input  wire [31:0]	b,          // Operand B (from rs2 or Immediate)
	input  wire [3:0]	ALUControl, // Control signals from Control Unit
	output reg  [31:0]	result,     // Final calculation output
	output wire         zero        // High if result is exactly 0 (for branches)
);

	// Signed variants of inputs for proper signed comparisons and arithmetic
	wire signed [31:0]	a_signed, b_signed;

	assign a_signed = a;
	assign b_signed = b;

	// The Zero flag is critical for conditional branch execution
	assign zero = (result == 32'h00000000) ? 1'b1 : 1'b0;

	always @(*) begin
		case (ALUControl)
			4'b0000: result = a + b;                                    // ADD / LW / SW / AUIPC
			4'b0001: result = a - b;                                    // SUB
			4'b0010: result = a & b;                                    // AND / ANDI
			4'b0011: result = a | b;                                    // OR / ORI
			4'b0100: result = a ^ b;                                    // XOR / XORI
			4'b0101: result = a << b[4:0];                              // SLL / SLLI (Shift Left Logical)
			4'b0110: result = a >> b[4:0];                              // SRL / SRLI (Shift Right Logical)
			4'b0111: result = $signed(a) >>> b[4:0];                             // SRA / SRAI (Shift Right Arithmetic)
			//4'b1000: result = (a == b) ? 32'h1 : 32'h0;                 // BEQ / BNE helper
			4'b1001: result = (a < b) ? 32'h1 : 32'h0;                  // SLTU / SLTIU (Less Than Unsigned)
			4'b1010: result = (a_signed < b_signed) ? 32'h1 : 32'h0;    // SLT / SLTI (Less Than Signed)
			//4'b1011: result = (a >= b) ? 32'h1 : 32'h0;                 // BGEU / BLTU helper
			//4'b1100: result = (a_signed >= b_signed) ? 32'h1 : 32'h0;   // BGE / BLT helper
			4'b1101: result = (a_signed + b_signed) & 32'hFFFFFFFE;     // JALR address alignment
			default: result = 32'h00000000;                            // Default safe state
		endcase
	end

endmodule

rtl/imm_gen.v
module imm_gen(
    input  wire [31:0] inst,
    input  wire [2:0]  immSel,
    output reg  [31:0] imm_out
);

    always @(*) begin
        case (immSel)

            // I-type: ADDI, LW, JALR, SLTI, XORI, ORI, ANDI, SLLI, SRLI, SRAI
            3'b001: begin
                imm_out = { {20{inst[31]}}, inst[31:20] };
            end

            // S-type: SW, SH, SB
            3'b010: begin
                imm_out = { {20{inst[31]}}, inst[31:25], inst[11:7] };
            end

            // B-type: BEQ, BNE, BLT, BGE, BLTU, BGEU
            3'b011: begin
                imm_out = { {19{inst[31]}}, inst[31], inst[7],
                            inst[30:25], inst[11:8], 1'b0 };
            end

            // U-type: LUI, AUIPC
            // Upper 20 bits go to imm[31:12], lower 12 bits are zero
            3'b100: begin
                imm_out = { inst[31:12], 12'b0 };
            end

            // J-type: JAL
            // Most scrambled encoding 
            3'b101: begin
                imm_out = { {11{inst[31]}}, inst[31], inst[19:12],
                            inst[20], inst[30:21], 1'b0 };
            end

            // Safe default
            default: begin
                imm_out = 32'h00000000;
            end

        endcase
    end

endmodule

rtl/regfile.v
module regfile(
    input  wire        clk,
    input  wire        reset,
    input  wire        w_enb,
    input  wire [4:0]  rs1,
    input  wire [4:0]  rs2,
    input  wire [4:0]  rd,
    input  wire [31:0] data,
    output wire [31:0] rdout1,
    output wire [31:0] rdout2
);
	
	reg [31:0] x [31:0];
	
	assign rdout1 = (rs1 == 0) ? 32'b0 : x[rs1];
    assign rdout2 = (rs2 == 0) ? 32'b0 : x[rs2];
	
	integer i;
	always @(posedge clk, posedge reset) begin
		if (reset) begin						// Reset
			for (i = 0; i < 32; i = i + 1) begin 
				x[i] <= 0;
			end
		end
		else if (w_enb & (rd != 0)) begin			// Write enable and can not overwrite x0
			x[rd] <= data;						// Store data to rd register
		end 
	
	end
	
endmodule

rtl/control_unit.v
module control_unit(
    input  wire [6:0] opcode,
    input  wire [2:0] funct3,
    input  wire [6:0] funct7,

    output reg regWrite,
    output reg memWrite,
    output reg memRead,
    output reg aluSrc,
    output reg branch,
    output reg memToReg,
    output reg [2:0] immSel,
    output reg [3:0] aluControl
);

    always @(*) begin

        // Safe defaults — prevents latches
        regWrite   = 0;
        memWrite   = 0;
        memRead    = 0;
        aluSrc     = 0;
        branch     = 0;
        memToReg   = 0;
        immSel     = 3'b000;
        aluControl = 4'b0000;

        case(opcode)

            // R-Type: ADD, SUB
            7'b0110011: begin
                regWrite = 1;
                aluSrc   = 0;
                case({funct7, funct3})
                    10'b0000000_000: aluControl = 4'b0000; // ADD
                    10'b0100000_000: aluControl = 4'b0001; // SUB
                    10'b0000000_111: aluControl = 4'b0010; // AND
                    10'b0000000_110: aluControl = 4'b0011; // OR
                    10'b0000000_100: aluControl = 4'b0100; // XOR
                    10'b0000000_001: aluControl = 4'b0101; // SLL
                    10'b0000000_101: aluControl = 4'b0110; // SRL
                    10'b0100000_101: aluControl = 4'b0111; // SRA
                    10'b0000000_010: aluControl = 4'b1010; // SLT
                    10'b0000000_011: aluControl = 4'b1001; // SLTU
                    default:         aluControl = 4'b0000;
                endcase
            end

            // I-Type: ADDI
            7'b0010011: begin
                regWrite   = 1;
                aluSrc     = 1;
                immSel     = 3'b001;
                aluControl = 4'b0000; // ADD (rs1 + imm)
            end

            // Load: LW
            7'b0000011: begin
                regWrite   = 1;
                memRead    = 1;
                memToReg   = 1;
                aluSrc     = 1;
                immSel     = 3'b001; // I-type immediate
                aluControl = 4'b0000; // ADD (base + offset)
            end

            // Store: SW
            7'b0100011: begin
                memWrite   = 1;
                aluSrc     = 1;
                immSel     = 3'b010; // S-type immediate
                aluControl = 4'b0000; // ADD (base + offset)
            end

            // Branch: BEQ
            7'b1100011: begin
                branch     = 1;
                aluSrc     = 0;
                immSel     = 3'b011; // B-type immediate
                aluControl = 4'b0001; // SUB (check zero flag)
            end

            default: begin
                // All signals already set to 0 above
            end

        endcase
    end

endmodule

rtl/inst_mem.v
module inst_mem(
    input  wire [31:0] addr,
    output wire [31:0] instruction
);

    // 64 words = 256 bytes
    // Valid PC range: 0x00000000 to 0x000000FC
    reg [31:0] rom [0:63];

    // Word-addressed: divide byte address by 4 using bits [7:2]
    assign instruction = rom[addr[7:2]];

    integer i;
    initial begin
        // Default to NOP so uninitialized memory is safe
        for (i = 0; i < 64; i = i + 1)
            rom[i] = 32'h00000013;
        $readmemh("prg/program.txt", rom);
    end

endmodule

rtl/pc.v
module pc(
    input  wire 		clk,         // Clock signal
    input  wire 		reset,       // System reset (sets PC back to 0)
    input  wire 		branch,      // Branch signal from Control Unit
    input  wire 		zero,        // Zero flag from ALU (asserted if rs1 == rs2)
    input  wire [31:0] 	imm_ext,     // Sign-extended branch immediate from imm_gen
    output reg  [31:0] 	curr_pc      // Current instruction address sent to Instruction Memory
);

    wire [31:0] pc_plus_4;
    wire [31:0] pc_branch;
    wire [31:0] next_pc;
    wire        branch_taken;

    // 1. Calculate standard next address sequential step (+4 bytes)
    assign pc_plus_4 = curr_pc + 32'd4;

    // 2. Calculate branch target address 
    assign pc_branch = curr_pc + imm_ext;

    // 3. Condition check: Is it a branch instruction AND did the comparison match?
    assign branch_taken = branch & zero;

    // 4. Multiplexer to select the true next address
    assign next_pc = (branch_taken) ? pc_branch : pc_plus_4;

    // 5. Sequential block to update the PC register on the clock edge
    always @(posedge clk) begin
        if (reset) begin
            curr_pc <= 32'h00000000; // Reset vector (starts program at address 0)
        end else begin
            curr_pc <= next_pc;      // Update to new address
        end
    end
    // fututre implementation for JAL , other branch instruction 


endmodule

rtl/datapath.v
module top ( 
    input wire clk, 
    input wire reset
    );

    wire [31:0] curr_pc; //current address of instruction 
    wire [31:0] instruction; //instruction

    wire [6:0]  opcode  = instruction[6:0];
    wire [4:0]  rd      = instruction[11:7];
    wire [2:0]  funct3  = instruction[14:12];
    wire [4:0]  rs1     = instruction[19:15];
    wire [4:0]  rs2     = instruction[24:20];
    wire [6:0]  funct7  = instruction[31:25];

    // Control unit output wires
    wire regWrite;
    wire memWrite;
    wire memRead;
    wire aluSrc;
    wire branch;
    wire memToReg;
    wire [2:0]  immSel;
    wire [3:0]  aluControl;

    // Register file wires
    wire [31:0] rdout1;   // rs1 value
    wire [31:0] rdout2;   // rs2 value

    // Immediate generator wire
    wire [31:0] imm_ext;

    // ALU wires
    wire [31:0] alu_b;     // ALU input B (rs2 or immediate)
    wire [31:0] alu_result;
    wire        zero;

    // Data memory wire
    wire [31:0] readData;

    // Writeback wire — what goes back into register file
    wire [31:0] writeBackData;

    //---------MUXES-------------
    // ALU input B mux: aluSrc=0 → rs2, aluSrc=1 → immediate
    assign alu_b = (aluSrc) ? imm_ext : rdout2;

    // Writeback mux: memToReg=0 → ALU result, memToReg=1 → memory data
    assign writeBackData = (memToReg) ? readData : alu_result;

    //module instantiation 
    pc program_counter (
        .clk(clk),
        .reset(reset),
        .branch(branch),       // From Control Unit
        .zero(zero),         // From ALU
        .imm_ext(imm_ext),      // From Immediate Generator
        .curr_pc(curr_pc) // Goes straight to instruction memory input address
    );

    //pc-> instruction address goes to instruction_memory
    inst_mem i_m (
        .addr(curr_pc),
        .instruction(instruction)
    );

    //decoder fetches opcode and gives control logic 
    control_unit CU (
        .opcode     (opcode),
        .funct3     (funct3),
        .funct7     (funct7),
        .regWrite   (regWrite),
        .memWrite   (memWrite),
        .memRead    (memRead),
        .aluSrc     (aluSrc),
        .branch     (branch),
        .memToReg   (memToReg),
        .immSel     (immSel),
        .aluControl (aluControl)
    );

    //reg file reads rada from register 
    regfile r_f(
        .clk(clk),
        .reset(reset),
        .w_enb(regWrite),
        .rs1(rs1),
        .rs2(rs2),
        .rd(rd),
        .data(writeBackData), //write back data
        .rdout1(rdout1),
        .rdout2(rdout2)
    );

    //immediate generator gives constant value as per type 
    imm_gen IMMGEN (
        .inst       (instruction),
        .immSel     (immSel),
        .imm_out    (imm_ext)
    );

    //now ALU computes 
    alu32 ALU (
        .a          (rdout1),
        .b          (alu_b),
        .ALUControl (aluControl),
        .result     (alu_result),
        .zero       (zero)
    );

    // Data Memory
    data_mem DMEM (
        .clk        (clk),
        .memRead    (memRead),
        .memWrite   (memWrite),
        .addr       (alu_result),
        .writeData  (rdout2),
        .readData   (readData)
    );

endmodule

tb/single_tb.v
module single_tb;

    reg clk;
    reg reset;

    top DUT (
        .clk   (clk),
        .reset (reset)
    );

    // Clock generation — 20ns period (50MHz)
    initial clk = 0;
    always #10 clk = ~clk;

    initial begin
        reset = 1;
        #20 reset = 0;
    end

    initial begin
        $dumpfile("sim/wave.vcd");
        $dumpvars(0, single_tb);
    end

    // Monitor — prints every time any signal changes
    initial begin
        $monitor("time=%0t | pc=%h | instr=%h | x1=%d x2=%d x3=%d x4=%d x5=%d x6=%d x7=%d x8=%d",
                  $time,
                  DUT.curr_pc,
                  DUT.instruction,
                  DUT.r_f.x[1],
                  DUT.r_f.x[2],
                  DUT.r_f.x[3],
                  DUT.r_f.x[4],
                  DUT.r_f.x[5],
                  DUT.r_f.x[6],
                  DUT.r_f.x[7],
                  DUT.r_f.x[8]);
    end
    // initial begin
    // $monitor("time=%0t | pc=%h | instr=%h | x1=%d x9=%d x10=%d x11=%d",
    //       $time,
    //       DUT.curr_pc,
    //       DUT.instruction,
    //       DUT.r_f.x[1],
    //       DUT.r_f.x[9],
    //       DUT.r_f.x[10],
    //       DUT.r_f.x[11]);
    // end 
    // Run simulation
    initial begin
        #300 $finish;
    end

endmodule

sim/wave.vcd
$date
	Tue Jun 16 22:20:03 2026
$end
$version
	Icarus Verilog
$end
$timescale
	1s
$end
$scope module single_tb $end
$var reg 1 ! clk $end
$var reg 1 " reset $end
$scope module DUT $end
$var wire 1 ! clk $end
$var wire 1 " reset $end
$var wire 1 # zero $end
$var wire 32 $ writeBackData [31:0] $end
$var wire 5 % rs2 [4:0] $end
$var wire 5 & rs1 [4:0] $end
$var wire 1 ' regWrite $end
$var wire 32 ( readData [31:0] $end
$var wire 32 ) rdout2 [31:0] $end
$var wire 32 * rdout1 [31:0] $end
$var wire 5 + rd [4:0] $end
$var wire 7 , opcode [6:0] $end
$var wire 1 - memWrite $end
$var wire 1 . memToReg $end
$var wire 1 / memRead $end
$var wire 32 0 instruction [31:0] $end
$var wire 32 1 imm_ext [31:0] $end
$var wire 3 2 immSel [2:0] $end
$var wire 7 3 funct7 [6:0] $end
$var wire 3 4 funct3 [2:0] $end
$var wire 32 5 curr_pc [31:0] $end
$var wire 1 6 branch $end
$var wire 32 7 alu_result [31:0] $end
$var wire 32 8 alu_b [31:0] $end
$var wire 1 9 aluSrc $end
$var wire 4 : aluControl [3:0] $end
$scope module ALU $end
$var wire 32 ; a_signed [31:0] $end
$var wire 32 < b [31:0] $end
$var wire 32 = b_signed [31:0] $end
$var wire 1 # zero $end
$var wire 32 > a [31:0] $end
$var wire 4 ? ALUControl [3:0] $end
$var reg 32 @ result [31:0] $end
$upscope $end
$scope module CU $end
$var wire 3 A funct3 [2:0] $end
$var wire 7 B funct7 [6:0] $end
$var wire 7 C opcode [6:0] $end
$var reg 4 D aluControl [3:0] $end
$var reg 1 9 aluSrc $end
$var reg 1 6 branch $end
$var reg 3 E immSel [2:0] $end
$var reg 1 / memRead $end
$var reg 1 . memToReg $end
$var reg 1 - memWrite $end
$var reg 1 ' regWrite $end
$upscope $end
$scope module DMEM $end
$var wire 32 F addr [31:0] $end
$var wire 1 ! clk $end
$var wire 1 / memRead $end
$var wire 1 - memWrite $end
$var wire 32 G writeData [31:0] $end
$var wire 32 H readData [31:0] $end
$var integer 32 I i [31:0] $end
$upscope $end
$scope module IMMGEN $end
$var wire 3 J immSel [2:0] $end
$var wire 32 K inst [31:0] $end
$var reg 32 L imm_out [31:0] $end
$upscope $end
$scope module i_m $end
$var wire 32 M instruction [31:0] $end
$var wire 32 N addr [31:0] $end
$var integer 32 O i [31:0] $end
$upscope $end
$scope module program_counter $end
$var wire 1 6 branch $end
$var wire 1 P branch_taken $end
$var wire 1 ! clk $end
$var wire 32 Q imm_ext [31:0] $end
$var wire 1 " reset $end
$var wire 1 # zero $end
$var wire 32 R pc_plus_4 [31:0] $end
$var wire 32 S pc_branch [31:0] $end
$var wire 32 T next_pc [31:0] $end
$var reg 32 U curr_pc [31:0] $end
$upscope $end
$scope module r_f $end
$var wire 1 ! clk $end
$var wire 32 V data [31:0] $end
$var wire 5 W rd [4:0] $end
$var wire 1 " reset $end
$var wire 5 X rs1 [4:0] $end
$var wire 5 Y rs2 [4:0] $end
$var wire 1 ' w_enb $end
$var wire 32 Z rdout2 [31:0] $end
$var wire 32 [ rdout1 [31:0] $end
$var integer 32 \ i [31:0] $end
$upscope $end
$upscope $end
$upscope $end
$enddefinitions $end
$comment Show the parameter values. $end
$dumpall
$end
#0
$dumpvars
b100000 \
bx [
bx Z
bx Y
bx X
bx W
bx V
bx U
bx T
bx S
bx R
bx Q
xP
b1000000 O
bx N
bx M
bx L
bx K
bx J
b1000000 I
bx H
bx G
bx F
bx E
bx D
bx C
bx B
bx A
bx @
bx ?
bx >
bx =
bx <
bx ;
bx :
x9
bx 8
bx 7
x6
bx 5
bx 4
bx 3
bx 2
bx 1
bx 0
x/
x.
x-
bx ,
bx +
bx *
bx )
bx (
x'
bx &
bx %
bx $
x#
1"
0!
$end
#10
0#
b101 $
b101 V
b101 7
b101 @
b101 F
0P
b101 =
b101 8
b101 <
b0 (
b0 H
b0 )
b0 G
b0 Z
b0 ;
b0 *
b0 >
b0 [
b0 :
b0 ?
b0 D
b1 2
b1 E
b1 J
0.
06
19
0/
0-
1'
b100 T
b0 3
b0 B
b101 %
b101 Y
b0 &
b0 X
b0 4
b0 A
b1 +
b1 W
b10011 ,
b10011 C
b101 S
b101 1
b101 L
b101 Q
b10100000000000010010011 0
b10100000000000010010011 K
b10100000000000010010011 M
b100 R
b0 5
b0 N
b0 U
b100000 \
1!
#20
0!
0"
#30
1#
b0 $
b0 V
b0 7
b0 @
b0 F
b0 2
b0 E
b0 J
09
0'
b0 =
b0 8
b0 <
b1000 %
b1000 Y
b101 +
b101 W
b1101111 ,
b1101111 C
b0 1
b0 L
b0 Q
b1000 T
b100000000000001011101111 0
b100000000000001011101111 K
b100000000000001011101111 M
b1000 R
b100 S
b100 5
b100 N
b100 U
1!
#40
0!
#50
0#
b1100011 $
b1100011 V
b1100011 7
b1100011 @
b1100011 F
b1100011 =
b1100011 8
b1100011 <
b1100011 1
b1100011 L
b1100011 Q
b1 2
b1 E
b1 J
19
1'
b11 3
b11 B
b11 %
b11 Y
b10 +
b10 W
b10011 ,
b10011 C
b1100 T
b110001100000000000100010011 0
b110001100000000000100010011 K
b110001100000000000100010011 M
b1100 R
b1101011 S
b1000 5
b1000 N
b1000 U
1!
#60
0!
#70
b110111 $
b110111 V
b110111 7
b110111 @
b110111 F
b1 2
b1 E
b1 J
19
1'
b110111 =
b110111 8
b110111 <
b1 3
b1 B
b10111 %
b10111 Y
b11 +
b11 W
b110111 1
b110111 L
b110111 Q
b10000 T
b11011100000000000110010011 0
b11011100000000000110010011 K
b11011100000000000110010011 M
b10000 R
b1000011 S
b1100 5
b1100 N
b1100 U
1!
#80
0!
#90
1#
b0 $
b0 V
b0 7
b0 @
b0 F
b1 2
b1 E
b1 J
19
1'
b0 =
b0 8
b0 <
b0 3
b0 B
b0 %
b0 Y
b0 +
b0 W
b0 1
b0 L
b0 Q
b10100 T
b10011 0
b10011 K
b10011 M
b10100 R
b10000 S
b10000 5
b10000 N
b10000 U
1!
#100
0!
#110
b11000 T
b11000 R
b10100 S
b10100 5
b10100 N
b10100 U
1!
#120
0!
#130
b11100 T
b11100 R
b11000 S
b11000 5
b11000 N
b11000 U
1!
#140
0!
#150
b100000 T
b100000 R
b11100 S
b11100 5
b11100 N
b11100 U
1!
#160
0!
#170
b100100 T
b100100 R
b100000 S
b100000 5
b100000 N
b100000 U
1!
#180
0!
#190
b101000 T
b101000 R
b100100 S
b100100 5
b100100 N
b100100 U
1!
#200
0!
#210
b101100 T
b101100 R
b101000 S
b101000 5
b101000 N
b101000 U
1!
#220
0!
#230
b110000 T
b110000 R
b101100 S
b101100 5
b101100 N
b101100 U
1!
#240
0!
#250
b110100 T
b110100 R
b110000 S
b110000 5
b110000 N
b110000 U
1!
#260
0!
#270
b111000 T
b111000 R
b110100 S
b110100 5
b110100 N
b110100 U
1!
#280
0!
#290
b111100 T
b111100 R
b111000 S
b111000 5
b111000 N
b111000 U
1!
